LICENSE
README.md
setup.cfg
setup.py
tilm/__init__.py
tilm.egg-info/PKG-INFO
tilm.egg-info/SOURCES.txt
tilm.egg-info/dependency_links.txt
tilm.egg-info/top_level.txt