Metadata-Version: 2.1
Name: tilm
Version: 0.0.2
Summary: Text-based web interface for language model
Home-page: UNKNOWN
Author: Qingyang Wu
Author-email: willqywu@gmail.com
License: UNKNOWN
Platform: UNKNOWN
Classifier: Programming Language :: Python :: 3
Classifier: License :: OSI Approved :: Apache Software License
Classifier: Operating System :: OS Independent
License-File: LICENSE
